[
  {
    "league": "ลาลีกา สเปน",
    "time": "02:00",
    "home": "ราโย บาเยกาโน่",
    "hLogo": "https://www.siamsport.co.th/static/team-logo/16098.png",
    "away": "เอลเช่",
    "aLogo": "https://www.siamsport.co.th/static/team-logo/16007.png",
    "status": "upcoming",
    "link": "https://www.siamsport.co.th/matches/3693289"
  },
  {
    "league": "ลีกเอิง ฝรั่งเศส",
    "time": "01:45",
    "home": "เปแอสเช",
    "hLogo": "https://www.siamsport.co.th/static/team-logo/10061.png",
    "away": "ตูลูส",
    "aLogo": "https://www.siamsport.co.th/static/team-logo/10134.png",
    "status": "upcoming",
    "link": "https://www.siamsport.co.th/matches/3690839"
  },
  {
    "league": "แชมเปี้ยนชิพ อังกฤษ",
    "time": "18:30",
    "home": "มิดเดิ้ลสโบรช์",
    "hLogo": "https://www.siamsport.co.th/static/team-logo/9274.png",
    "away": "มิลล์วอลล์",
    "aLogo": "https://www.siamsport.co.th/static/team-logo/9276.png",
    "status": "upcoming",
    "link": "https://www.siamsport.co.th/matches/3691628"
  },
  {
    "league": "แชมเปี้ยนชิพ อังกฤษ",
    "time": "21:00",
    "home": "เชฟฯ ยูไนเต็ด",
    "hLogo": "https://www.siamsport.co.th/static/team-logo/9348.png",
    "away": "สวอนซี ซิตี้",
    "aLogo": "https://www.siamsport.co.th/static/team-logo/9387.png",
    "status": "upcoming",
    "link": "https://www.siamsport.co.th/matches/3691631"
  },
  {
    "league": "แชมเปี้ยนชิพ อังกฤษ",
    "time": "21:00",
    "home": "สโต๊ค ซิตี้",
    "hLogo": "https://www.siamsport.co.th/static/team-logo/9378.png",
    "away": "เชฟฟิลด์ เว้นส์เดย์",
    "aLogo": "https://www.siamsport.co.th/static/team-logo/9349.png",
    "status": "upcoming",
    "link": "https://www.siamsport.co.th/matches/3691629"
  },
  {
    "league": "แชมเปี้ยนชิพ อังกฤษ",
    "time": "21:00",
    "home": "เบอร์มิงแฮม ซิตี้",
    "hLogo": "https://www.siamsport.co.th/static/team-logo/9039.png",
    "away": "แบล็คเบิร์น โรเวอร์ส",
    "aLogo": "https://www.siamsport.co.th/static/team-logo/9044.png",
    "status": "upcoming",
    "link": "https://www.siamsport.co.th/matches/3691627"
  },
  {
    "league": "แชมเปี้ยนชิพ อังกฤษ",
    "time": "21:00",
    "home": "ชาร์ลตัน",
    "hLogo": "https://www.siamsport.co.th/static/team-logo/9088.png",
    "away": "บริสตอล ซิตี้",
    "aLogo": "https://www.siamsport.co.th/static/team-logo/9066.png",
    "status": "upcoming",
    "link": "https://www.siamsport.co.th/matches/3691626"
  },
  {
    "league": "แชมเปี้ยนชิพ อังกฤษ",
    "time": "21:00",
    "home": "เวสต์บรอมวิช อัลเบี้ยน",
    "hLogo": "https://www.siamsport.co.th/static/team-logo/9426.png",
    "away": "เร็กซ์แฮม",
    "aLogo": "https://www.siamsport.co.th/static/team-logo/9453.png",
    "status": "upcoming",
    "link": "https://www.siamsport.co.th/matches/3691624"
  },
  {
    "league": "แชมเปี้ยนชิพ อังกฤษ",
    "time": "21:00",
    "home": "ควีนส์พาร์ค เรนเจอร์ส",
    "hLogo": "https://www.siamsport.co.th/static/team-logo/9318.png",
    "away": "วัตฟอร์ด",
    "aLogo": "https://www.siamsport.co.th/static/team-logo/9423.png",
    "status": "upcoming",
    "link": "https://www.siamsport.co.th/matches/3691623"
  },
  {
    "league": "แชมเปี้ยนชิพ อังกฤษ",
    "time": "21:00",
    "home": "เลสเตอร์ ซิตี้",
    "hLogo": "https://www.siamsport.co.th/static/team-logo/9240.png",
    "away": "เปรสตัน นอร์ธเอนด์",
    "aLogo": "https://www.siamsport.co.th/static/team-logo/9317.png",
    "status": "upcoming",
    "link": "https://www.siamsport.co.th/matches/3691622"
  },
  {
    "league": "แชมเปี้ยนชิพ อังกฤษ",
    "time": "21:00",
    "home": "นอริช ซิตี้",
    "hLogo": "https://www.siamsport.co.th/static/team-logo/9296.png",
    "away": "พอร์ทสมัธ",
    "aLogo": "https://www.siamsport.co.th/static/team-logo/9314.png",
    "status": "upcoming",
    "link": "https://www.siamsport.co.th/matches/3691621"
  },
  {
    "league": "แชมเปี้ยนชิพ อังกฤษ",
    "time": "21:00",
    "home": "อ็อกซ์ฟอร์ด ยูไนเต็ด",
    "hLogo": "https://www.siamsport.co.th/static/team-logo/9306.png",
    "away": "ฮัลล์ ซิตี้",
    "aLogo": "https://www.siamsport.co.th/static/team-logo/9221.png",
    "status": "upcoming",
    "link": "https://www.siamsport.co.th/matches/3691620"
  },
  {
    "league": "แชมเปี้ยนชิพ อังกฤษ",
    "time": "02:00",
    "home": "โคเวนทรี ซิตี้",
    "hLogo": "https://www.siamsport.co.th/static/team-logo/9116.png",
    "away": "ดาร์บี้ เคาน์ตี้",
    "aLogo": "https://www.siamsport.co.th/static/team-logo/9133.png",
    "status": "upcoming",
    "link": "https://www.siamsport.co.th/matches/3691630"
  }
]